repobee_csvgrades/__init__.py
repobee_csvgrades/__version.py
repobee_csvgrades/_containers.py
repobee_csvgrades/_exception.py
repobee_csvgrades/_file.py
repobee_csvgrades/_grades.py
repobee_csvgrades/_marker.py
repobee_csvgrades/csvgrades.py
repobee_csvgrades-0.2.1.dist-info/LICENSE
repobee_csvgrades-0.2.1.dist-info/METADATA
repobee_csvgrades-0.2.1.dist-info/WHEEL
repobee_csvgrades-0.2.1.dist-info/top_level.txt
repobee_csvgrades-0.2.1.dist-info/RECORD
