Metadata-Version: 2.1
Name: repobee-csvgrades
Version: 0.2.1
Summary: A plugin for reporting grades into a CSV file based on issue titles
Home-page: https://github.com/slarse/repobee-csvgrades
Author: Simon Larsén
Author-email: slarse@kth.se
License: MIT
Download-URL: https://github.com/slarse/repobee-csvgrades/archive/v0.2.1.tar.gz
Platform: UNKNOWN
Requires-Python: >=3.6
Requires-Dist: repobee (>=3.5.0)
Requires-Dist: dataclasses (>='0.7') ; python_version < "3.7"
Provides-Extra: test
Requires-Dist: pytest ; extra == 'test'
Requires-Dist: pytest-cov ; extra == 'test'
Requires-Dist: pytest-mock ; extra == 'test'
Requires-Dist: tox ; extra == 'test'
